strava_map/__init__.py
strava_map/activities.py
strava_map/map.py
strava_map/strava_heatmap.py
strava_map/stravauth/__init__.py
strava_map/stravauth/stravauth.py
tests/__init__.py
tests/test_activities.py
tests/test_map.py
strava_map-0.1.0.dist-info/LICENSE
strava_map-0.1.0.dist-info/METADATA
strava_map-0.1.0.dist-info/WHEEL
strava_map-0.1.0.dist-info/top_level.txt
strava_map-0.1.0.dist-info/RECORD
