Metadata-Version: 2.1
Name: strava-map
Version: 0.1.0
Summary: Create maps from your Strava Activities
Home-page: https://github.com/tcramm0nd/strava_map
Author: tcramm0nd
Author-email: 25987791+tcramm0nd@users.noreply.github.com
License: MIT
Platform: UNKNOWN
Classifier: License :: OSI Approved :: MIT License
Classifier: Programming Language :: Python :: 3
Classifier: Programming Language :: Python :: 3.7
Requires-Dist: folium (>=0.12.1)
Requires-Dist: loguru (==0.5.3)
Requires-Dist: pandas (>=1.2.1)
Requires-Dist: polyline (>=1.4.0)
